{
  "name": "braintree-web",
  "version": "2.12.2",
  "authors": [
    "braintree <code@getbraintree.com>"
  ],
  "description": "A suite of tools for integrating Braintree in the browser",
  "main": "dist/braintree.js",
  "moduleType": [
    "amd",
    "globals",
    "node"
  ],
  "repository": {
    "type": "git",
    "url": "git@github.com:braintree/braintree-web"
  },
  "keywords": [
    "braintree",
    "payments"
  ],
  "license": "MIT",
  "homepage": "https://github.com/braintree/braintree-web",
  "ignore": [
    "*",
    "!dist/braintree.js"
  ],
  "_release": "2.12.2",
  "_resolution": {
    "type": "version",
    "tag": "2.12.2",
    "commit": "81e04193f57328857485f8dded3b57398c510efe"
  },
  "_source": "git://github.com/braintree/braintree-web.git",
  "_target": "^2.0",
  "_originalSource": "braintree/braintree-web"
}